LICENSE
MANIFEST.in
README.markdown
setup.cfg
setup.py
django_medusa/__init__.py
django_medusa/utils.py
django_medusa.egg-info/PKG-INFO
django_medusa.egg-info/SOURCES.txt
django_medusa.egg-info/dependency_links.txt
django_medusa.egg-info/requires.txt
django_medusa.egg-info/top_level.txt
django_medusa/management/__init__.py
django_medusa/management/commands/__init__.py
django_medusa/management/commands/staticsitegen.py
django_medusa/renderers/__init__.py
django_medusa/renderers/appengine.py
django_medusa/renderers/base.py
django_medusa/renderers/disk.py
django_medusa/renderers/s3.py