Metadata-Version: 1.1
Name: django-medusa
Version: 0.2.0
Summary: A Django static website generator.
Home-page: https://github.com/mtigas/django-medusa/
Author: Mike Tigas
Author-email: mike@tig.as
License: MIT
Download-URL: https://github.com/mtigas/django-medusa/downloads
Keywords: django static staticwebsite staticgenerator publishing
Platform: UNKNOWN
Classifier: Development Status :: 3 - Alpha
Classifier: License :: OSI Approved :: MIT License
Classifier: Operating System :: OS Independent
Classifier: Programming Language :: Python
Classifier: Topic :: Software Development :: Libraries :: Python Modules
